{
"meta":{"test_sets":[],"test_metrics":[],"learn_metrics":[{"best_value":"Min","name":"Logloss"}],"launch_mode":"Train","parameters":"","iteration_count":100,"learn_sets":["learn"],"name":"experiment"},
"iterations":[
{"learn":[0.6298072998],"iteration":0,"passed_time":0.1497337638,"remaining_time":14.82364261},
{"learn":[0.5814208496],"iteration":1,"passed_time":0.156097154,"remaining_time":7.648760548},
{"learn":[0.5434765564],"iteration":2,"passed_time":0.1631496988,"remaining_time":5.275173595},
{"learn":[0.516620636],"iteration":3,"passed_time":0.1708899396,"remaining_time":4.10135855},
{"learn":[0.4923575195],"iteration":4,"passed_time":0.1773222136,"remaining_time":3.369122059},
{"learn":[0.4740963867],"iteration":5,"passed_time":0.1840496256,"remaining_time":2.883444135},
{"learn":[0.4600487366],"iteration":6,"passed_time":0.1911360324,"remaining_time":2.539378716},
{"learn":[0.447840686],"iteration":7,"passed_time":0.1980069872,"remaining_time":2.277080353},
{"learn":[0.439462323],"iteration":8,"passed_time":0.2041929563,"remaining_time":2.064617669},
{"learn":[0.433051825],"iteration":9,"passed_time":0.210194061,"remaining_time":1.891746549},
{"learn":[0.4269467407],"iteration":10,"passed_time":0.2172969783,"remaining_time":1.758130097},
{"learn":[0.4222264893],"iteration":11,"passed_time":0.2237854417,"remaining_time":1.641093239},
{"learn":[0.4183350861],"iteration":12,"passed_time":0.2302297634,"remaining_time":1.540768417},
{"learn":[0.4144669159],"iteration":13,"passed_time":0.2364176023,"remaining_time":1.452279557},
{"learn":[0.4113472351],"iteration":14,"passed_time":0.2420831125,"remaining_time":1.371804304},
{"learn":[0.4085907043],"iteration":15,"passed_time":0.250272674,"remaining_time":1.313931539},
{"learn":[0.4063615021],"iteration":16,"passed_time":0.2564585488,"remaining_time":1.25212115},
{"learn":[0.4043998199],"iteration":17,"passed_time":0.2635429388,"remaining_time":1.200584499},
{"learn":[0.4025655426],"iteration":18,"passed_time":0.2693084972,"remaining_time":1.148104646},
{"learn":[0.4011950684],"iteration":19,"passed_time":0.2750696771,"remaining_time":1.100278709},
{"learn":[0.4001026794],"iteration":20,"passed_time":0.2824094432,"remaining_time":1.062397429},
{"learn":[0.398337384],"iteration":21,"passed_time":0.2882643371,"remaining_time":1.022028104},
{"learn":[0.3974645721],"iteration":22,"passed_time":0.2954105065,"remaining_time":0.9889830002},
{"learn":[0.3963108307],"iteration":23,"passed_time":0.3010705591,"remaining_time":0.9533901037},
{"learn":[0.3955575165],"iteration":24,"passed_time":0.308681381,"remaining_time":0.926044143},
{"learn":[0.3948996277],"iteration":25,"passed_time":0.3150430438,"remaining_time":0.8966609708},
{"learn":[0.3940306061],"iteration":26,"passed_time":0.3215165316,"remaining_time":0.8692854372},
{"learn":[0.3932643585],"iteration":27,"passed_time":0.3285722934,"remaining_time":0.8449001831},
{"learn":[0.39248508],"iteration":28,"passed_time":0.334245877,"remaining_time":0.8183261128},
{"learn":[0.3921170959],"iteration":29,"passed_time":0.3421943779,"remaining_time":0.7984535484},
{"learn":[0.3910882782],"iteration":30,"passed_time":0.3480511139,"remaining_time":0.7746944147},
{"learn":[0.3906564209],"iteration":31,"passed_time":0.3541453006,"remaining_time":0.7525587638},
{"learn":[0.3898150452],"iteration":32,"passed_time":0.3611353875,"remaining_time":0.7332142716},
{"learn":[0.3895487213],"iteration":33,"passed_time":0.367300287,"remaining_time":0.7129946748},
{"learn":[0.3893419159],"iteration":34,"passed_time":0.3750824415,"remaining_time":0.6965816771},
{"learn":[0.3890932007],"iteration":35,"passed_time":0.3808513264,"remaining_time":0.6770690247},
{"learn":[0.3888540894],"iteration":36,"passed_time":0.3885273271,"remaining_time":0.6615465299},
{"learn":[0.3885038544],"iteration":37,"passed_time":0.3941446979,"remaining_time":0.6430781914},
{"learn":[0.3880770111],"iteration":38,"passed_time":0.4005555971,"remaining_time":0.6265100364},
{"learn":[0.3878313904],"iteration":39,"passed_time":0.4085112624,"remaining_time":0.6127668937},
{"learn":[0.3876069427],"iteration":40,"passed_time":0.4143606838,"remaining_time":0.5962751303},
{"learn":[0.3874196228],"iteration":41,"passed_time":0.4215063334,"remaining_time":0.5820801747},
{"learn":[0.38715401],"iteration":42,"passed_time":0.4274471526,"remaining_time":0.566615993},
{"learn":[0.3870394653],"iteration":43,"passed_time":0.4347803568,"remaining_time":0.5533568177},
{"learn":[0.3860708862],"iteration":44,"passed_time":0.441457517,"remaining_time":0.5395591875},
{"learn":[0.3858524506],"iteration":45,"passed_time":0.4471198142,"remaining_time":0.5248797819},
{"learn":[0.3856983673],"iteration":46,"passed_time":0.4543660296,"remaining_time":0.5123702036},
{"learn":[0.3855859924],"iteration":47,"passed_time":0.461280753,"remaining_time":0.4997208157},
{"learn":[0.3853571259],"iteration":48,"passed_time":0.4678235028,"remaining_time":0.4869183397},
{"learn":[0.3852068878],"iteration":49,"passed_time":0.4740344979,"remaining_time":0.4740344979},
{"learn":[0.3846809265],"iteration":50,"passed_time":0.4805961124,"remaining_time":0.461749206},
{"learn":[0.384578299],"iteration":51,"passed_time":0.4876799001,"remaining_time":0.4501660616},
{"learn":[0.3844422424],"iteration":52,"passed_time":0.4941692057,"remaining_time":0.438225522},
{"learn":[0.3843171417],"iteration":53,"passed_time":0.5005372631,"remaining_time":0.4263835945},
{"learn":[0.383770874],"iteration":54,"passed_time":0.5064503233,"remaining_time":0.4143684464},
{"learn":[0.3835881897],"iteration":55,"passed_time":0.5121037016,"remaining_time":0.4023671941},
{"learn":[0.3834974823],"iteration":56,"passed_time":0.5195140502,"remaining_time":0.3919141081},
{"learn":[0.3833711456],"iteration":57,"passed_time":0.5252314889,"remaining_time":0.3803400437},
{"learn":[0.3832324554],"iteration":58,"passed_time":0.5318333442,"remaining_time":0.3695791036},
{"learn":[0.3831543976],"iteration":59,"passed_time":0.5375923906,"remaining_time":0.3583949271},
{"learn":[0.3828856232],"iteration":60,"passed_time":0.5434840045,"remaining_time":0.34747338},
{"learn":[0.3824001953],"iteration":61,"passed_time":0.5524301844,"remaining_time":0.3385862421},
{"learn":[0.3822110107],"iteration":62,"passed_time":0.5581424452,"remaining_time":0.327797944},
{"learn":[0.3821128693],"iteration":63,"passed_time":0.5650653122,"remaining_time":0.3178492381},
{"learn":[0.3818253998],"iteration":64,"passed_time":0.570633813,"remaining_time":0.3072643609},
{"learn":[0.3814752991],"iteration":65,"passed_time":0.5774557428,"remaining_time":0.2974772008},
{"learn":[0.38132435],"iteration":66,"passed_time":0.5836692924,"remaining_time":0.2874789052},
{"learn":[0.3812405609],"iteration":67,"passed_time":0.589346961,"remaining_time":0.2773397464},
{"learn":[0.3811789215],"iteration":68,"passed_time":0.5967409699,"remaining_time":0.2681010155},
{"learn":[0.3810147217],"iteration":69,"passed_time":0.603215349,"remaining_time":0.2585208639},
{"learn":[0.3808753693],"iteration":70,"passed_time":0.6104107516,"remaining_time":0.2493227014},
{"learn":[0.3807670654],"iteration":71,"passed_time":0.6162662744,"remaining_time":0.2396591067},
{"learn":[0.3807113739],"iteration":72,"passed_time":0.6385471344,"remaining_time":0.2361749675},
{"learn":[0.3805550262],"iteration":73,"passed_time":0.6457593787,"remaining_time":0.2268884304},
{"learn":[0.3803496643],"iteration":74,"passed_time":0.6518729216,"remaining_time":0.2172909739},
{"learn":[0.3802373566],"iteration":75,"passed_time":0.6582275506,"remaining_time":0.2078613318},
{"learn":[0.3801776947],"iteration":76,"passed_time":0.6643567811,"remaining_time":0.1984442333},
{"learn":[0.3800787842],"iteration":77,"passed_time":0.6705538821,"remaining_time":0.1891305821},
{"learn":[0.3799694275],"iteration":78,"passed_time":0.6774580291,"remaining_time":0.1800837799},
{"learn":[0.3798874603],"iteration":79,"passed_time":0.6829803895,"remaining_time":0.1707450974},
{"learn":[0.3797386597],"iteration":80,"passed_time":0.6900190199,"remaining_time":0.1618563133},
{"learn":[0.3796519318],"iteration":81,"passed_time":0.6975213784,"remaining_time":0.1531144489},
{"learn":[0.3795431396],"iteration":82,"passed_time":0.7041849368,"remaining_time":0.1442306497},
{"learn":[0.3794430054],"iteration":83,"passed_time":0.7112669847,"remaining_time":0.1354794257},
{"learn":[0.3793669098],"iteration":84,"passed_time":0.7172084903,"remaining_time":0.1265662042},
{"learn":[0.3788734802],"iteration":85,"passed_time":0.7247169438,"remaining_time":0.1179771769},
{"learn":[0.3787615326],"iteration":86,"passed_time":0.7309321228,"remaining_time":0.1092197425},
{"learn":[0.3784742645],"iteration":87,"passed_time":0.7380710277,"remaining_time":0.1006460492},
{"learn":[0.378429306],"iteration":88,"passed_time":0.7438788646,"remaining_time":0.09194008439},
{"learn":[0.3783021454],"iteration":89,"passed_time":0.7496653328,"remaining_time":0.08329614809},
{"learn":[0.3782301636],"iteration":90,"passed_time":0.7575306014,"remaining_time":0.07492060893},
{"learn":[0.3781297211],"iteration":91,"passed_time":0.7629695415,"remaining_time":0.06634517752},
{"learn":[0.3780523743],"iteration":92,"passed_time":0.7695864756,"remaining_time":0.05792586376},
{"learn":[0.377947522],"iteration":93,"passed_time":0.7754629275,"remaining_time":0.04949763367},
{"learn":[0.3778732239],"iteration":94,"passed_time":0.7818411091,"remaining_time":0.04114953206},
{"learn":[0.3777904236],"iteration":95,"passed_time":0.7891203676,"remaining_time":0.03288001532},
{"learn":[0.3776399628],"iteration":96,"passed_time":0.7952385086,"remaining_time":0.02459500542},
{"learn":[0.377578656],"iteration":97,"passed_time":0.8021697771,"remaining_time":0.01637081178},
{"learn":[0.3775138214],"iteration":98,"passed_time":0.807965113,"remaining_time":0.008161263768},
{"learn":[0.3772898621],"iteration":99,"passed_time":0.8141750172,"remaining_time":0}
]}